LICENSE
MANIFEST.in
README.md
clockr
clockr.1
setup.py
version.py
clockr/__init__.py
clockr/__version__.py
clockr/clockr.py
clockr.egg-info/PKG-INFO
clockr.egg-info/SOURCES.txt
clockr.egg-info/dependency_links.txt
clockr.egg-info/entry_points.txt
clockr.egg-info/top_level.txt