Metadata-Version: 1.1
Name: clockr
Version: 1.0
Summary: Simple curses clock written in Python
Home-page: https://github.com/shaggytwodope/clockr
Author: Johnathan "ShaggyTwoDope" Jenkins
Author-email: twodopeshaggy@gmail.com
License: MIT
Keywords: clock terminal time curses
Platform: UNKNOWN
Classifier: Intended Audience :: End Users/Desktop
Classifier: Programming Language :: Python :: 3
